hyperepo/__init__.py
hyperepo/cli.py
hyperepo/core.py
hyperepo/exceptions.py
hyperepo/templates/__init__.py
hyperepo/templates/base.py
hyperepo-0.0.1.dist-info/LICENSE
hyperepo-0.0.1.dist-info/METADATA
hyperepo-0.0.1.dist-info/WHEEL
hyperepo-0.0.1.dist-info/entry_points.txt
hyperepo-0.0.1.dist-info/RECORD
