Metadata-Version: 2.3
Name: hyperepo
Version: 0.0.1
Summary: Monorepo pattern with symlinked meta repositories for clean documentation management
License: MIT
Keywords: monorepo,git,documentation,development,workflow
Author: Tyson
Author-email: tyson@example.com
Requires-Python: >=3.8,<4.0
Classifier: Development Status :: 2 - Pre-Alpha
Classifier: Intended Audience :: Developers
Classifier: License :: OSI Approved :: MIT License
Classifier: Programming Language :: Python :: 3
Classifier: Programming Language :: Python :: 3.8
Classifier: Programming Language :: Python :: 3.9
Classifier: Programming Language :: Python :: 3.10
Classifier: Programming Language :: Python :: 3.11
Classifier: Programming Language :: Python :: 3.12
Classifier: Programming Language :: Python :: 3.13
Classifier: Topic :: Software Development :: Libraries :: Python Modules
Classifier: Topic :: Software Development :: Version Control
Requires-Dist: click (>=8.0.0,<9.0.0)
Requires-Dist: pyyaml (>=6.0,<7.0)
Project-URL: Documentation, https://github.com/tysonzero/hyperepo
Project-URL: Homepage, https://github.com/tysonzero/hyperepo
Project-URL: Repository, https://github.com/tysonzero/hyperepo
